{
  "date": "2023-11-12",
  "rates": {
    "AED": 3.673,
    "AFN": 73.249032,
    "ALL": 97.475624,
    "AMD": 401.194841,
    "ANG": 1.79581,
    "AOA": 831.5,
    "ARS": 348.717591,
    "AUD": 1.5721,
    "AWG": 1.8025,
    "AZN": 1.705396,
    "BAM": 1.825207,
    "BBD": 2,
    "BDT": 109.85021,
    "BGN": 1.830246,
    "BHD": 0.375624,
    "BIF": 2830.941497,
    "BMD": 1,
    "BND": 1.35542,
    "BOB": 6.885353,
    "BRL": 4.9063,
    "BSD": 1,
    "BTC": 0.000026974558,
    "BTN": 82.996776,
    "BWP": 13.584061,
    "BYN": 3.282721,
    "BZD": 2.008492,
    "CAD": 1.38015,
    "CDF": 2472.102757,
    "CHF": 0.902888,
    "CLF": 0.03315,
    "CLP": 914.703,
    "CNH": 7.30508,
    "CNY": 7.2891,
    "COP": 4028.6501,
    "CRC": 529.046792,
    "CUC": 1,
    "CUP": 25.75,
    "CVE": 102.90235,
    "CZK": 22.9575,
    "DJF": 177.40657,
    "DKK": 6.9788,
    "DOP": 56.656246,
    "DZD": 134.492463,
    "EGP": 30.788951,
    "ERN": 15,
    "ETB": 55.708739,
    "EUR": 0.933264,
    "FJD": 2.278,
    "FKP": 0.81813,
    "GBP": 0.81813,
    "GEL": 2.695,
    "GGP": 0.81813,
    "GHS": 11.896785,
    "GIP": 0.81813,
    "GMD": 67.275,
    "GNF": 8560.565256,
    "GTQ": 7.797116,
    "GYD": 208.464382,
    "HKD": 7.80915,
    "HNL": 24.613877,
    "HRK": 7.05168,
    "HTG": 132.647243,
    "HUF": 352.433155,
    "IDR": 15694.05,
    "ILS": 3.853016,
    "IMP": 0.81813,
    "INR": 83.29425,
    "IQD": 1305.302729,
    "IRR": 42262.5,
    "ISK": 141.47726,
    "JEP": 0.81813,
    "JMD": 155.35437,
    "JOD": 0.7093,
    "JPY": 151.525,
    "KES": 151.752123,
    "KGS": 89.32,
    "KHR": 4125,
    "KMF": 461.499977,
    "KPW": 900,
    "KRW": 1320.17,
    "KWD": 0.307685,
    "KYD": 0.830386,
    "KZT": 465.755555,
    "LAK": 20679.528757,
    "LBP": 14975.862492,
    "LKR": 326.340216,
    "LRD": 187.650056,
    "LSL": 18.67603,
    "LYD": 4.85185,
    "MAD": 10.203351,
    "MDL": 17.835846,
    "MGA": 4519.581069,
    "MKD": 57.500817,
    "MMK": 2092.4767,
    "MNT": 3450,
    "MOP": 8.014372,
    "MRO": 356.999828,
    "MRU": 39.517522,
    "MUR": 44.212683,
    "MVR": 15.32,
    "MWK": 1114.722863,
    "MXN": 17.6465,
    "MYR": 4.708,
    "MZN": 63.850001,
    "NAD": 18.66,
    "NGN": 800.150177,
    "NIO": 36.470534,
    "NOK": 11.047305,
    "NPR": 132.794546,
    "NZD": 1.698849,
    "OMR": 0.383557,
    "PAB": 1,
    "PEN": 3.787784,
    "PGK": 3.70118,
    "PHP": 55.920499,
    "PKR": 282.082991,
    "PLN": 4.14409,
    "PYG": 7417.323905,
    "QAR": 3.635761,
    "RON": 4.6511,
    "RSD": 109.346264,
    "RUB": 92.180001,
    "RWF": 1225.140485,
    "SAR": 3.751047,
    "SBD": 8.405736,
    "SCR": 13.261537,
    "SDG": 599.5,
    "SEK": 10.8987,
    "SGD": 1.3609,
    "SHP": 0.81813,
    "SLL": 20969.5,
    "SOS": 569.455903,
    "SRD": 37.9565,
    "SSP": 130.26,
    "STD": 22281.8,
    "STN": 22.864075,
    "SVC": 8.718212,
    "SYP": 2512.53,
    "SZL": 18.671084,
    "THB": 35.812608,
    "TJS": 10.930615,
    "TMT": 3.51,
    "TND": 3.1465,
    "TOP": 2.39283,
    "TRY": 28.558399,
    "TTD": 6.7687,
    "TWD": 32.3608,
    "TZS": 2491.06696,
    "UAH": 35.977792,
    "UGX": 3756.253961,
    "USD": 1,
    "UYU": 39.886654,
    "UZS": 12226.36818,
    "VES": 35.201783,
    "VND": 24324.987514,
    "VUV": 118.722,
    "WST": 2.8,
    "XAF": 612.180918,
    "XAG": 0.04492565,
    "XAU": 0.000516,
    "XCD": 2.70255,
    "XDR": 0.757967,
    "XOF": 612.180918,
    "XPD": 0.00103467,
    "XPF": 111.367994,
    "XPT": 0.00118995,
    "YER": 250.300053,
    "ZAR": 18.7325,
    "ZMW": 22.742756,
    "ZWL": 322
  }
}