{
  "date": "2023-04-14",
  "rates": {
    "AED": 3.6723,
    "AFN": 86.376573,
    "ALL": 102.172873,
    "AMD": 392.944656,
    "ANG": 1.803546,
    "AOA": 506.9775,
    "ARS": 214.5731,
    "AUD": 1.47632,
    "AWG": 1.8,
    "AZN": 1.7,
    "BAM": 1.769987,
    "BBD": 2,
    "BDT": 106.498691,
    "BGN": 1.769005,
    "BHD": 0.37699,
    "BIF": 2083.257297,
    "BMD": 1,
    "BND": 1.326643,
    "BOB": 6.914651,
    "BRL": 4.9296,
    "BSD": 1,
    "BTC": 0.000032430495,
    "BTN": 81.846471,
    "BWP": 13.08182,
    "BYN": 2.526413,
    "BZD": 2.017203,
    "CAD": 1.33243,
    "CDF": 2086.51224,
    "CHF": 0.889049,
    "CLF": 0.028774,
    "CLP": 793.95,
    "CNH": 6.852943,
    "CNY": 6.8541,
    "COP": 4412.650817,
    "CRC": 536.720491,
    "CUC": 1,
    "CUP": 25.75,
    "CVE": 99.783689,
    "CZK": 21.12085,
    "DJF": 178.182745,
    "DKK": 6.740735,
    "DOP": 54.89369,
    "DZD": 135.176772,
    "EGP": 30.903,
    "ERN": 15,
    "ETB": 54.505836,
    "EUR": 0.904637,
    "FJD": 2.1974,
    "FKP": 0.800453,
    "GBP": 0.800453,
    "GEL": 2.52,
    "GGP": 0.800453,
    "GHS": 11.299021,
    "GIP": 0.800453,
    "GMD": 62.291667,
    "GNF": 8602.034253,
    "GTQ": 7.803302,
    "GYD": 211.654532,
    "HKD": 7.84995,
    "HNL": 24.611305,
    "HRK": 6.816797,
    "HTG": 155.613595,
    "HUF": 338.21,
    "IDR": 14734.1,
    "ILS": 3.657737,
    "IMP": 0.800453,
    "INR": 81.72335,
    "IQD": 1461,
    "IRR": 42250,
    "ISK": 135.43,
    "JEP": 0.800453,
    "JMD": 152.455298,
    "JOD": 0.7099,
    "JPY": 132.610125,
    "KES": 134.6,
    "KGS": 87.52,
    "KHR": 4065.899261,
    "KMF": 445.54984,
    "KPW": 900,
    "KRW": 1301.158391,
    "KWD": 0.306043,
    "KYD": 0.833993,
    "KZT": 451.619904,
    "LAK": 17213.040295,
    "LBP": 15021.80493,
    "LKR": 323.253619,
    "LRD": 162.799971,
    "LSL": 18.079893,
    "LYD": 4.759319,
    "MAD": 10.160039,
    "MDL": 17.932485,
    "MGA": 4372.696912,
    "MKD": 55.938091,
    "MMK": 2101.539873,
    "MNT": 3519,
    "MOP": 8.092019,
    "MRO": 356.999828,
    "MRU": 34.285246,
    "MUR": 45,
    "MVR": 15.36,
    "MWK": 1027.159437,
    "MXN": 18.074137,
    "MYR": 4.402,
    "MZN": 63.899991,
    "NAD": 18.41,
    "NGN": 460.795628,
    "NIO": 36.606668,
    "NOK": 10.3215,
    "NPR": 130.953403,
    "NZD": 1.591964,
    "OMR": 0.384951,
    "PAB": 1,
    "PEN": 3.780389,
    "PGK": 3.5718,
    "PHP": 55.280493,
    "PKR": 281.08472,
    "PLN": 4.202712,
    "PYG": 7148.119835,
    "QAR": 3.6405,
    "RON": 4.4716,
    "RSD": 106.09,
    "RUB": 81.632653,
    "RWF": 1107.376674,
    "SAR": 3.751199,
    "SBD": 8.286119,
    "SCR": 13.138098,
    "SDG": 600,
    "SEK": 10.270167,
    "SGD": 1.32666,
    "SHP": 0.800453,
    "SLL": 17665,
    "SOS": 568.963836,
    "SRD": 36.877,
    "SSP": 130.26,
    "STD": 22823.990504,
    "STN": 22.171043,
    "SVC": 8.75664,
    "SYP": 2512.53,
    "SZL": 18.077092,
    "THB": 34.07,
    "TJS": 10.927971,
    "TMT": 3.5,
    "TND": 3.0275,
    "TOP": 2.34455,
    "TRY": 19.372456,
    "TTD": 6.795198,
    "TWD": 30.453999,
    "TZS": 2346.692,
    "UAH": 36.961121,
    "UGX": 3732.890253,
    "USD": 1,
    "UYU": 38.697181,
    "UZS": 11450.843809,
    "VES": 24.457307,
    "VND": 23449.410804,
    "VUV": 118.979,
    "WST": 2.72551,
    "XAF": 593.402916,
    "XAG": 0.03847782,
    "XAU": 0.00049181,
    "XCD": 2.70255,
    "XDR": 0.740332,
    "XOF": 593.402916,
    "XPD": 0.00067152,
    "XPF": 107.951899,
    "XPT": 0.0009539,
    "YER": 250.275042,
    "ZAR": 18.052949,
    "ZMW": 18.238171,
    "ZWL": 322
  }
}