{
  "date": "2023-08-11",
  "rates": {
    "AED": 3.67304,
    "AFN": 84.131532,
    "ALL": 94.410827,
    "AMD": 387.830253,
    "ANG": 1.802083,
    "AOA": 824.917,
    "ARS": 286.1737,
    "AUD": 1.531754,
    "AWG": 1.8025,
    "AZN": 1.7,
    "BAM": 1.779051,
    "BBD": 2,
    "BDT": 109.455591,
    "BGN": 1.7785,
    "BHD": 0.377012,
    "BIF": 2834.13143,
    "BMD": 1,
    "BND": 1.35007,
    "BOB": 6.909819,
    "BRL": 4.893,
    "BSD": 1,
    "BTC": 0.00003400422,
    "BTN": 82.846961,
    "BWP": 13.495247,
    "BYN": 2.524128,
    "BZD": 2.015737,
    "CAD": 1.344105,
    "CDF": 2481.013243,
    "CHF": 0.874666,
    "CLF": 0.030668,
    "CLP": 846.21,
    "CNH": 7.253142,
    "CNY": 7.2323,
    "COP": 3950.048633,
    "CRC": 538.498843,
    "CUC": 1,
    "CUP": 25.75,
    "CVE": 100.300188,
    "CZK": 21.916632,
    "DJF": 178.034474,
    "DKK": 6.775364,
    "DOP": 56.74656,
    "DZD": 135.735355,
    "EGP": 30.9037,
    "ERN": 15,
    "ETB": 55.146575,
    "EUR": 0.90931,
    "FJD": 2.2447,
    "FKP": 0.785334,
    "GBP": 0.785334,
    "GEL": 2.610496,
    "GGP": 0.785334,
    "GHS": 11.173769,
    "GIP": 0.785334,
    "GMD": 60.383401,
    "GNF": 8595.121003,
    "GTQ": 7.864841,
    "GYD": 209.195526,
    "HKD": 7.816028,
    "HNL": 24.598172,
    "HRK": 6.851031,
    "HTG": 136.49884,
    "HUF": 347.907474,
    "IDR": 15278.695117,
    "ILS": 3.725324,
    "IMP": 0.785334,
    "INR": 82.768749,
    "IQD": 1309.771489,
    "IRR": 42250,
    "ISK": 131.58,
    "JEP": 0.785334,
    "JMD": 154.600472,
    "JOD": 0.7081,
    "JPY": 144.481,
    "KES": 142.202149,
    "KGS": 87.87,
    "KHR": 4134.289889,
    "KMF": 447.340547,
    "KPW": 900,
    "KRW": 1326.13602,
    "KWD": 0.307501,
    "KYD": 0.833235,
    "KZT": 446.682338,
    "LAK": 19435.64638,
    "LBP": 15009.39796,
    "LKR": 321.017045,
    "LRD": 186.663001,
    "LSL": 18.84832,
    "LYD": 4.795561,
    "MAD": 9.771249,
    "MDL": 17.594877,
    "MGA": 4506.794727,
    "MKD": 56.074296,
    "MMK": 2099.7754,
    "MNT": 3450,
    "MOP": 8.050389,
    "MRO": 356.999828,
    "MRU": 37.891673,
    "MUR": 45.15,
    "MVR": 15.343001,
    "MWK": 1085.1774,
    "MXN": 16.997534,
    "MYR": 4.587,
    "MZN": 63.830001,
    "NAD": 18.817066,
    "NGN": 769.2,
    "NIO": 36.585256,
    "NOK": 10.375581,
    "NPR": 132.55536,
    "NZD": 1.663365,
    "OMR": 0.384999,
    "PAB": 1,
    "PEN": 3.667288,
    "PGK": 3.633635,
    "PHP": 56.500509,
    "PKR": 288.373756,
    "PLN": 4.034459,
    "PYG": 7266.155011,
    "QAR": 3.645791,
    "RON": 4.4931,
    "RSD": 106.641,
    "RUB": 98.437999,
    "RWF": 1179.771721,
    "SAR": 3.752007,
    "SBD": 8.36879,
    "SCR": 13.307145,
    "SDG": 601.5,
    "SEK": 10.732575,
    "SGD": 1.349555,
    "SHP": 0.785334,
    "SLL": 20969.5,
    "SOS": 569.466724,
    "SRD": 38.1855,
    "SSP": 130.26,
    "STD": 22281.8,
    "STN": 22.285896,
    "SVC": 8.749716,
    "SYP": 2512.53,
    "SZL": 18.833856,
    "THB": 35.048333,
    "TJS": 10.964027,
    "TMT": 3.5,
    "TND": 3.08748,
    "TOP": 2.372383,
    "TRY": 27.047999,
    "TTD": 6.78703,
    "TWD": 31.828499,
    "TZS": 2505.026,
    "UAH": 36.928102,
    "UGX": 3618.666076,
    "USD": 1,
    "UYU": 37.967889,
    "UZS": 11709.017821,
    "VES": 31.107505,
    "VND": 23758.617861,
    "VUV": 118.722,
    "WST": 2.7185,
    "XAF": 596.468249,
    "XAG": 0.04399859,
    "XAU": 0.00052111,
    "XCD": 2.70255,
    "XDR": 0.747987,
    "XOF": 596.468249,
    "XPD": 0.00075222,
    "XPF": 108.509545,
    "XPT": 0.0010932,
    "YER": 250.21,
    "ZAR": 18.815137,
    "ZMW": 19.068625,
    "ZWL": 322
  }
}