{
  "date": "2023-12-12",
  "rates": {
    "AED": 3.6725,
    "AFN": 69.253172,
    "ALL": 94.493595,
    "AMD": 403.348037,
    "ANG": 1.802812,
    "AOA": 830.594333,
    "ARS": 365.8348,
    "AUD": 1.517596,
    "AWG": 1.8025,
    "AZN": 1.7,
    "BAM": 1.816848,
    "BBD": 2,
    "BDT": 110.034546,
    "BGN": 1.812895,
    "BHD": 0.376916,
    "BIF": 2846.484956,
    "BMD": 1,
    "BND": 1.343261,
    "BOB": 6.91228,
    "BRL": 4.9349,
    "BSD": 1,
    "BTC": 0.000024065886,
    "BTN": 83.39902,
    "BWP": 13.702931,
    "BYN": 3.295664,
    "BZD": 2.016396,
    "CAD": 1.356602,
    "CDF": 2720.879201,
    "CHF": 0.875202,
    "CLF": 0.031948,
    "CLP": 881.38,
    "CNH": 7.18154,
    "CNY": 7.1704,
    "COP": 3974.550682,
    "CRC": 527.085825,
    "CUC": 1,
    "CUP": 25.75,
    "CVE": 102.430138,
    "CZK": 22.622057,
    "DJF": 178.109119,
    "DKK": 6.907137,
    "DOP": 57.028195,
    "DZD": 134.360534,
    "EGP": 30.8991,
    "ERN": 15,
    "ETB": 56.24156,
    "EUR": 0.926205,
    "FJD": 2.2342,
    "FKP": 0.795516,
    "GBP": 0.795516,
    "GEL": 2.67,
    "GGP": 0.795516,
    "GHS": 12.033554,
    "GIP": 0.795516,
    "GMD": 67.4,
    "GNF": 8597.424341,
    "GTQ": 7.830077,
    "GYD": 209.449159,
    "HKD": 7.809215,
    "HNL": 24.669179,
    "HRK": 6.978779,
    "HTG": 132.161637,
    "HUF": 354.14497,
    "IDR": 15611.655927,
    "ILS": 3.70805,
    "IMP": 0.795516,
    "INR": 83.374116,
    "IQD": 1310.386484,
    "IRR": 42262.5,
    "ISK": 139.96,
    "JEP": 0.795516,
    "JMD": 155.617539,
    "JOD": 0.7093,
    "JPY": 145.17772727,
    "KES": 154.754417,
    "KGS": 89.32,
    "KHR": 4115.269528,
    "KMF": 457.399599,
    "KPW": 900,
    "KRW": 1309.314623,
    "KWD": 0.308331,
    "KYD": 0.833651,
    "KZT": 459.037091,
    "LAK": 20736.439,
    "LBP": 15030.061003,
    "LKR": 327.366224,
    "LRD": 188.14998,
    "LSL": 19.119252,
    "LYD": 4.836155,
    "MAD": 10.168975,
    "MDL": 17.886157,
    "MGA": 4586.188634,
    "MKD": 57.068098,
    "MMK": 2100.647233,
    "MNT": 3450,
    "MOP": 8.043215,
    "MRO": 356.999828,
    "MRU": 39.07068,
    "MUR": 44.2,
    "MVR": 15.37,
    "MWK": 1683.906578,
    "MXN": 17.348571,
    "MYR": 4.6845,
    "MZN": 63.850001,
    "NAD": 19.08,
    "NGN": 789.5,
    "NIO": 36.609895,
    "NOK": 10.892025,
    "NPR": 133.438925,
    "NZD": 1.62662,
    "OMR": 0.384957,
    "PAB": 1,
    "PEN": 3.742923,
    "PGK": 3.729732,
    "PHP": 55.600004,
    "PKR": 283.942458,
    "PLN": 4.019854,
    "PYG": 7353.603043,
    "QAR": 3.641,
    "RON": 4.6059,
    "RSD": 108.530799,
    "RUB": 89.812005,
    "RWF": 1248.504659,
    "SAR": 3.750811,
    "SBD": 8.454445,
    "SCR": 13.592701,
    "SDG": 601,
    "SEK": 10.439177,
    "SGD": 1.340363,
    "SHP": 0.795516,
    "SLL": 20969.5,
    "SOS": 571.674505,
    "SRD": 37.4835,
    "SSP": 130.26,
    "STD": 22281.8,
    "STN": 22.759258,
    "SVC": 8.752682,
    "SYP": 2512.53,
    "SZL": 19.111452,
    "THB": 35.69,
    "TJS": 10.938522,
    "TMT": 3.5,
    "TND": 3.13,
    "TOP": 2.3648,
    "TRY": 29.039201,
    "TTD": 6.797217,
    "TWD": 31.43625,
    "TZS": 2500,
    "UAH": 36.898424,
    "UGX": 3804.036187,
    "USD": 1,
    "UYU": 39.322323,
    "UZS": 12331.08815,
    "VES": 35.580297,
    "VND": 24268.902622,
    "VUV": 118.722,
    "WST": 2.8,
    "XAF": 607.550891,
    "XAG": 0.04356663,
    "XAU": 0.00050294,
    "XCD": 2.70255,
    "XDR": 0.752449,
    "XOF": 607.550891,
    "XPD": 0.00102173,
    "XPF": 110.5257,
    "XPT": 0.00108177,
    "YER": 250.325036,
    "ZAR": 18.930371,
    "ZMW": 24.333124,
    "ZWL": 322
  }
}