{
  "date": "2025-11-18",
  "rates": {
    "AED": 3.6725,
    "AFN": 66.33595,
    "ALL": 83.380062,
    "AMD": 382.458692,
    "ANG": 1.79,
    "AOA": 912.085,
    "ARS": 1386.9941,
    "AUD": 1.537745,
    "AWG": 1.8,
    "AZN": 1.7,
    "BAM": 1.687358,
    "BBD": 2,
    "BDT": 122.363241,
    "BGN": 1.6884,
    "BHD": 0.37706,
    "BIF": 2954.409844,
    "BMD": 1,
    "BND": 1.303016,
    "BOB": 6.94079,
    "BRL": 5.3289,
    "BSD": 1,
    "BTC": 0.00001093772,
    "BTN": 88.629772,
    "BWP": 14.227667,
    "BYN": 3.414647,
    "BZD": 2.01295,
    "CAD": 1.403106,
    "CDF": 2196.95187,
    "CHF": 0.796921,
    "CLF": 0.023558,
    "CLP": 924.21,
    "CNH": 7.113277,
    "CNY": 7.1113,
    "COP": 3760.530791,
    "CRC": 501.337093,
    "CUC": 1,
    "CUP": 25.75,
    "CVE": 95.131471,
    "CZK": 20.870849,
    "DJF": 178.233862,
    "DKK": 6.446737,
    "DOP": 64.343022,
    "DZD": 130.411869,
    "EGP": 47.161546,
    "ERN": 15,
    "ETB": 156.30502,
    "EUR": 0.863204,
    "FJD": 2.28425,
    "FKP": 0.760978,
    "GBP": 0.760978,
    "GEL": 2.705,
    "GGP": 0.760978,
    "GHS": 11,
    "GIP": 0.760978,
    "GMD": 73.000001,
    "GNF": 8691.384077,
    "GTQ": 7.669876,
    "GYD": 209.405652,
    "HKD": 7.786004,
    "HNL": 26.331002,
    "HRK": 6.503706,
    "HTG": 131.103969,
    "HUF": 332.248565,
    "IDR": 16757.474781,
    "ILS": 3.267905,
    "IMP": 0.760978,
    "INR": 88.570548,
    "IQD": 1311.198303,
    "IRR": 42125,
    "ISK": 127.06,
    "JEP": 0.760978,
    "JMD": 160.555596,
    "JOD": 0.709,
    "JPY": 155.4275,
    "KES": 129.75,
    "KGS": 87.45,
    "KHR": 4011.800206,
    "KMF": 424.999927,
    "KPW": 900,
    "KRW": 1463.572847,
    "KWD": 0.306986,
    "KYD": 0.834103,
    "KZT": 522.815067,
    "LAK": 21715.253022,
    "LBP": 89637.749105,
    "LKR": 307.27428,
    "LRD": 181.16092,
    "LSL": 17.083069,
    "LYD": 5.456843,
    "MAD": 9.244062,
    "MDL": 16.972262,
    "MGA": 4481.906914,
    "MKD": 53.080436,
    "MMK": 2099.7,
    "MNT": 3582.15,
    "MOP": 8.013528,
    "MRO": 356.999828,
    "MRU": 39.765335,
    "MUR": 45.869997,
    "MVR": 15.41,
    "MWK": 1735.561894,
    "MXN": 18.4389,
    "MYR": 4.164,
    "MZN": 63.959999,
    "NAD": 17.083142,
    "NGN": 1446.57,
    "NIO": 36.830616,
    "NOK": 10.13452,
    "NPR": 141.804841,
    "NZD": 1.764962,
    "OMR": 0.384491,
    "PAB": 1,
    "PEN": 3.373408,
    "PGK": 4.230869,
    "PHP": 58.901002,
    "PKR": 282.862675,
    "PLN": 3.66235,
    "PYG": 7046.018974,
    "QAR": 3.648238,
    "RON": 4.3904,
    "RSD": 101.130509,
    "RUB": 81.025727,
    "RWF": 1455.273804,
    "SAR": 3.750232,
    "SBD": 8.230592,
    "SCR": 13.884189,
    "SDG": 601.5,
    "SEK": 9.491656,
    "SGD": 1.302599,
    "SHP": 0.760978,
    "SLL": 20969.5,
    "SOS": 571.047266,
    "SRD": 38.6165,
    "SSP": 130.26,
    "STD": 22281.8,
    "STN": 21.137089,
    "SVC": 8.757619,
    "SYP": 13002,
    "SZL": 17.078032,
    "THB": 32.43,
    "TJS": 9.24833,
    "TMT": 3.5,
    "TND": 2.947079,
    "TOP": 2.40776,
    "TRY": 42.342182,
    "TTD": 6.786358,
    "TWD": 31.186401,
    "TZS": 2442.632,
    "UAH": 42.094804,
    "UGX": 3576.104533,
    "USD": 1,
    "UYU": 39.79141,
    "UZS": 12049.81997,
    "VES": 236.164592,
    "VND": 26381.744292,
    "VUV": 122.16,
    "WST": 2.816,
    "XAF": 566.224563,
    "XAG": 0.0198787,
    "XAU": 0.00024755,
    "XCD": 2.70255,
    "XDR": 0.703819,
    "XOF": 566.224563,
    "XPD": 0.00071056,
    "XPF": 103.007611,
    "XPT": 0.00065246,
    "YER": 238.550083,
    "ZAR": 17.203798,
    "ZMW": 22.695293,
    "ZWL": 322,
    "SLE": 23.375,
    "XCG": 1.803806,
    "ZWG": 26.407
  }
}