{
  "date": "2022-08-19",
  "rates": {
    "AED": 3.67302,
    "AFN": 88.253283,
    "ALL": 116.508629,
    "AMD": 402.703122,
    "ANG": 1.802658,
    "AOA": 429.84305,
    "ARS": 135.7479,
    "AUD": 1.451337,
    "AWG": 1.8025,
    "AZN": 1.7,
    "BAM": 1.945122,
    "BBD": 2,
    "BDT": 95.03359,
    "BGN": 1.947065,
    "BHD": 0.377037,
    "BIF": 2062.486223,
    "BMD": 1,
    "BND": 1.39073,
    "BOB": 6.916823,
    "BRL": 5.1685,
    "BSD": 1,
    "BTC": 0.000046662604,
    "BTN": 79.764693,
    "BWP": 12.759424,
    "BYN": 2.524204,
    "BZD": 2.016201,
    "CAD": 1.29946,
    "CDF": 1999.669463,
    "CHF": 0.956805,
    "CLF": 0.033667,
    "CLP": 928.98,
    "CNH": 6.840835,
    "CNY": 6.8182,
    "COP": 4393.752831,
    "CRC": 666.442493,
    "CUC": 1,
    "CUP": 25.75,
    "CVE": 109.3,
    "CZK": 24.505802,
    "DJF": 178.069682,
    "DKK": 7.40119,
    "DOP": 53.788353,
    "DZD": 141.582256,
    "EGP": 19.1457,
    "ERN": 15,
    "ETB": 52.736887,
    "EUR": 0.995168,
    "FJD": 2.20365,
    "FKP": 0.845062,
    "GBP": 0.845062,
    "GEL": 2.765,
    "GGP": 0.845062,
    "GHS": 9.821693,
    "GIP": 0.845062,
    "GMD": 54.25,
    "GNF": 8631.907276,
    "GTQ": 7.741903,
    "GYD": 209.387249,
    "HKD": 7.845785,
    "HNL": 24.608285,
    "HRK": 7.4795,
    "HTG": 129.532651,
    "HUF": 405.24059,
    "IDR": 14871.850135,
    "ILS": 3.2703,
    "IMP": 0.845062,
    "INR": 79.90152,
    "IQD": 1459.857738,
    "IRR": 42350,
    "ISK": 139.84,
    "JEP": 0.845062,
    "JMD": 151.372211,
    "JOD": 0.709,
    "JPY": 137.024,
    "KES": 119.76,
    "KGS": 81.60465,
    "KHR": 4102.963564,
    "KMF": 487.150305,
    "KPW": 900,
    "KRW": 1336.54589,
    "KWD": 0.307424,
    "KYD": 0.833511,
    "KZT": 476.676311,
    "LAK": 15252.447644,
    "LBP": 1512.557321,
    "LKR": 360.089722,
    "LRD": 153.549955,
    "LSL": 16.87629,
    "LYD": 4.885207,
    "MAD": 10.38334,
    "MDL": 19.244957,
    "MGA": 4206.12552,
    "MKD": 60.621713,
    "MMK": 2100.530579,
    "MNT": 3195.360782,
    "MOP": 8.083221,
    "MRO": 356.999828,
    "MRU": 37.709409,
    "MUR": 46.005385,
    "MVR": 15.35,
    "MWK": 1026.702604,
    "MXN": 20.250799,
    "MYR": 4.4765,
    "MZN": 63.850001,
    "NAD": 16.65,
    "NGN": 425.855506,
    "NIO": 35.949101,
    "NOK": 9.798675,
    "NPR": 127.62319,
    "NZD": 1.611565,
    "OMR": 0.384979,
    "PAB": 1,
    "PEN": 3.846028,
    "PGK": 3.524463,
    "PHP": 56.014501,
    "PKR": 215.703679,
    "PLN": 4.72711,
    "PYG": 6880.252781,
    "QAR": 3.641,
    "RON": 4.8576,
    "RSD": 116.798935,
    "RUB": 59.012497,
    "RWF": 1030.683843,
    "SAR": 3.755614,
    "SBD": 8.217066,
    "SCR": 12.870829,
    "SDG": 569.5,
    "SEK": 10.55619,
    "SGD": 1.390765,
    "SHP": 0.845062,
    "SLL": 13748.9,
    "SOS": 568.669162,
    "SRD": 24.335,
    "SSP": 130.26,
    "STD": 22392.090504,
    "STN": 24.375,
    "SVC": 8.751821,
    "SYP": 2512.53,
    "SZL": 16.87629,
    "THB": 35.796999,
    "TJS": 10.222625,
    "TMT": 3.51,
    "TND": 3.161,
    "TOP": 2.3423,
    "TRY": 18.108175,
    "TTD": 6.782761,
    "TWD": 30.105501,
    "TZS": 2332.605121,
    "UAH": 36.744719,
    "UGX": 3846.018169,
    "USD": 1,
    "UYU": 40.400191,
    "UZS": 10919.690208,
    "VES": 5.969,
    "VND": 23402.762808,
    "VUV": 115.95454,
    "WST": 2.6644,
    "XAF": 652.787716,
    "XAG": 0.05185243,
    "XAU": 0.00057043,
    "XCD": 2.70255,
    "XDR": 0.738776,
    "XOF": 652.787716,
    "XPD": 0.00046687,
    "XPF": 118.755186,
    "XPT": 0.00110498,
    "YER": 250.249937,
    "ZAR": 17.02205,
    "ZMW": 16.129208,
    "ZWL": 322
  }
}