{
  "date": "2024-01-19",
  "rates": {
    "AED": 3.6729,
    "AFN": 73.023412,
    "ALL": 95.335652,
    "AMD": 405.42,
    "ANG": 1.802816,
    "AOA": 830.592033,
    "ARS": 819.24251,
    "AUD": 1.515268,
    "AWG": 1.8025,
    "AZN": 1.7,
    "BAM": 1.796372,
    "BBD": 2,
    "BDT": 109.768074,
    "BGN": 1.796439,
    "BHD": 0.376937,
    "BIF": 2852.237753,
    "BMD": 1,
    "BND": 1.344075,
    "BOB": 6.911661,
    "BRL": 4.9313,
    "BSD": 1,
    "BTC": 0.000024135505,
    "BTN": 83.142889,
    "BWP": 13.656386,
    "BYN": 3.273546,
    "BZD": 2.016306,
    "CAD": 1.347098,
    "CDF": 2745.785871,
    "CHF": 0.868962,
    "CLF": 0.033001,
    "CLP": 910.45,
    "CNH": 7.201593,
    "CNY": 7.1138,
    "COP": 3965.009626,
    "CRC": 515.821631,
    "CUC": 1,
    "CUP": 25.75,
    "CVE": 101.291136,
    "CZK": 22.7504,
    "DJF": 178.104416,
    "DKK": 6.849724,
    "DOP": 58.857841,
    "DZD": 134.372619,
    "EGP": 30.9002,
    "ERN": 15,
    "ETB": 56.4,
    "EUR": 0.918483,
    "FJD": 2.2352,
    "FKP": 0.788566,
    "GBP": 0.788566,
    "GEL": 2.655,
    "GGP": 0.788566,
    "GHS": 12.003546,
    "GIP": 0.788566,
    "GMD": 67.275,
    "GNF": 8597.723383,
    "GTQ": 7.817488,
    "GYD": 209.435147,
    "HKD": 7.81935,
    "HNL": 24.710001,
    "HRK": 6.920372,
    "HTG": 131.651603,
    "HUF": 350.560497,
    "IDR": 15595.756314,
    "ILS": 3.73338,
    "IMP": 0.788566,
    "INR": 83.068659,
    "IQD": 1310.415571,
    "IRR": 42045,
    "ISK": 136.59,
    "JEP": 0.788566,
    "JMD": 155.202899,
    "JOD": 0.7094,
    "JPY": 147.979,
    "KES": 162,
    "KGS": 89.3175,
    "KHR": 4082.463603,
    "KMF": 453.000277,
    "KPW": 900,
    "KRW": 1333.20003,
    "KWD": 0.307768,
    "KYD": 0.833651,
    "KZT": 451.870828,
    "LAK": 20655,
    "LBP": 15062.5,
    "LKR": 321.303983,
    "LRD": 189.250025,
    "LSL": 18.91,
    "LYD": 4.82,
    "MAD": 9.968446,
    "MDL": 17.730764,
    "MGA": 4561,
    "MKD": 56.508979,
    "MMK": 2100.636873,
    "MNT": 3450,
    "MOP": 8.058754,
    "MRO": 356.999828,
    "MRU": 39.55,
    "MUR": 44.25,
    "MVR": 15.4,
    "MWK": 1683,
    "MXN": 17.143744,
    "MYR": 4.7175,
    "MZN": 63.850001,
    "NAD": 18.91,
    "NGN": 860.5,
    "NIO": 36.73,
    "NOK": 10.468077,
    "NPR": 133.034135,
    "NZD": 1.634004,
    "OMR": 0.384941,
    "PAB": 1,
    "PEN": 3.746406,
    "PGK": 3.740739,
    "PHP": 56.006995,
    "PKR": 280.1,
    "PLN": 4.015283,
    "PYG": 7291.152792,
    "QAR": 3.64085,
    "RON": 4.5721,
    "RSD": 107.660007,
    "RUB": 88.339223,
    "RWF": 1273,
    "SAR": 3.750712,
    "SBD": 8.425461,
    "SCR": 13.40877,
    "SDG": 601,
    "SEK": 10.453712,
    "SGD": 1.340886,
    "SHP": 0.788566,
    "SLL": 20969.5,
    "SOS": 571.664591,
    "SRD": 36.95,
    "SSP": 130.26,
    "STD": 22281.8,
    "STN": 22.75,
    "SVC": 8.752647,
    "SYP": 2512.53,
    "SZL": 18.91,
    "THB": 35.4595,
    "TJS": 10.928131,
    "TMT": 3.5,
    "TND": 3.1115,
    "TOP": 2.366775,
    "TRY": 30.190936,
    "TTD": 6.792304,
    "TWD": 31.392498,
    "TZS": 2515,
    "UAH": 37.672177,
    "UGX": 3803.972549,
    "USD": 1,
    "UYU": 39.291418,
    "UZS": 12440,
    "VES": 36.001566,
    "VND": 24548.917039,
    "VUV": 118.722,
    "WST": 2.8,
    "XAF": 602.485555,
    "XAG": 0.04385878,
    "XAU": 0.00049224,
    "XCD": 2.70255,
    "XDR": 0.751461,
    "XOF": 602.485555,
    "XPD": 0.00105699,
    "XPF": 109.604213,
    "XPT": 0.00109765,
    "YER": 250.350066,
    "ZAR": 18.991614,
    "ZMW": 26.373011,
    "ZWL": 322
  }
}